pyimgurapi/__init__.py
pyimgurapi/api.py
pyimgurapi/endpoints/__init__.py
pyimgurapi/endpoints/account.py
pyimgurapi/endpoints/album.py
pyimgurapi/endpoints/base_endpoint.py
pyimgurapi/endpoints/comment.py
pyimgurapi/endpoints/feed.py
pyimgurapi/endpoints/gallery.py
pyimgurapi/endpoints/image.py
pyimgurapi/exceptions.py
pyimgurapi/form_factories.py
pyimgurapi/utils.py
pyimgurapi-0.5.0.dist-info/LICENSE
pyimgurapi-0.5.0.dist-info/METADATA
pyimgurapi-0.5.0.dist-info/WHEEL
pyimgurapi-0.5.0.dist-info/RECORD
