Metadata-Version: 2.1
Name: pyimgurapi
Version: 0.5.0
Summary: A Python SDK for the Imgur API.
Home-page: https://github.com/nautics889/PyImgurApi
License: MIT
Author: nautics889
Author-email: cyberukr@gmail.com
Requires-Python: >=3.8,<4.0
Classifier: License :: OSI Approved :: MIT License
Classifier: Programming Language :: Python :: 3
Classifier: Programming Language :: Python :: 3.8
Classifier: Programming Language :: Python :: 3.9
Classifier: Programming Language :: Python :: 3.10
Classifier: Programming Language :: Python :: 3.11
Project-URL: Repository, https://github.com/nautics889/PyImgurApi
